<repast.simphony.data2.engine.DataSetDescriptor simphonyVersion="2.5.0">
  <name>Money</name>
  <type>AGGREGATE</type>
  <inclTick>true</inclTick>
  <inclBatchRun>false</inclBatchRun>
  <inclRandomSeed>false</inclRandomSeed>
  <scheduleParams>
    <start>1.0</start>
    <interval>1.0</interval>
    <priority>-Infinity</priority>
    <pType>LAST</pType>
    <duration>-1.0</duration>
    <frequency>REPEAT</frequency>
    <hashCode>654059871</hashCode>
  </scheduleParams>
  <atEnd>false</atEnd>
  <methodDataSources class="linked-hash-map">
    <entry>
      <string>HBalance</string>
      <repast.simphony.data2.engine.MethodDataSourceDefinition>
        <id>HBalance</id>
        <className>agents.Household</className>
        <methodName>getBalance</methodName>
        <aggType>SUM</aggType>
      </repast.simphony.data2.engine.MethodDataSourceDefinition>
    </entry>
    <entry>
      <string>FBalance</string>
      <repast.simphony.data2.engine.MethodDataSourceDefinition>
        <id>FBalance</id>
        <className>agents.Firm</className>
        <methodName>getBalance</methodName>
        <aggType>SUM</aggType>
      </repast.simphony.data2.engine.MethodDataSourceDefinition>
    </entry>
    <entry>
      <string>GovBalance</string>
      <repast.simphony.data2.engine.MethodDataSourceDefinition>
        <id>GovBalance</id>
        <className>agents.Government</className>
        <methodName>getFunds</methodName>
        <aggType>SUM</aggType>
      </repast.simphony.data2.engine.MethodDataSourceDefinition>
    </entry>
  </methodDataSources>
  <countSources class="linked-hash-map"/>
  <customNADataSources class="linked-hash-map"/>
  <customAggDataSources class="linked-hash-map"/>
</repast.simphony.data2.engine.DataSetDescriptor>